my_simple_tools/__init__.py
my_simple_tools/helloworld.py
my_simple_tools-0.1.dist-info/LICENSE
my_simple_tools-0.1.dist-info/METADATA
my_simple_tools-0.1.dist-info/WHEEL
my_simple_tools-0.1.dist-info/top_level.txt
my_simple_tools-0.1.dist-info/RECORD
